{
  "type": "coat",
  "name": "Ornate mail .",
  "system": {
    "description": "",
    "armor": 1,
    "equipped": false
  },
  "folder": "i53mIHsFkNycKrJS",
  "img": "systems/mythicbastionland/tokens/items/coat.png",
  "effects": [],
  "flags": {},
  "_stats": {
    "systemId": "mythicbastionland",
    "systemVersion": "1.0.8",
    "coreVersion": "13.348",
    "createdTime": 1707686406901,
    "modifiedTime": 1756662987716,
    "lastModifiedBy": "KQJsJtxYaymNehvs",
    "compendiumSource": null,
    "duplicateSource": null,
    "exportSource": null
  },
  "_id": "ikZPP3goDOVb83rO",
  "sort": 0,
  "ownership": {
    "default": 0
  },
  "_key": "!items!ikZPP3goDOVb83rO"
}
