{
  "type": "ability",
  "name": "Pain Strike",
  "system": {
    "description": "Make a melee Attack on your own. Damage is applied to GD as normal, but then to SPI in place of VIG. If the target loses half of their SPI from this Attack they lie broken before you."
  },
  "folder": "P9tsnQbPwgaF4cnH",
  "img": "systems/mythicbastionland/tokens/items/ability.png",
  "effects": [],
  "flags": {},
  "_stats": {
    "systemId": "mythicbastionland",
    "systemVersion": "1.0.8",
    "coreVersion": "13.348",
    "createdTime": 1707686408215,
    "modifiedTime": 1756662987716,
    "lastModifiedBy": "KQJsJtxYaymNehvs",
    "compendiumSource": null,
    "duplicateSource": null,
    "exportSource": null
  },
  "_id": "t7TPSn2Y1D6d6ygL",
  "sort": 0,
  "ownership": {
    "default": 0
  },
  "_key": "!items!t7TPSn2Y1D6d6ygL"
}
