{
  "type": "ability",
  "name": "Sunder Memory",
  "system": {
    "description": "When you Wound a target you can rob them of a single specific memory. If it is a Mortal Wound then you can remove all memory of a specific place, thing, person, or event."
  },
  "folder": "xntYFomQNcoEbLdk",
  "img": "systems/mythicbastionland/tokens/items/ability.png",
  "effects": [],
  "flags": {},
  "_stats": {
    "systemId": "mythicbastionland",
    "systemVersion": "1.0.8",
    "coreVersion": "13.348",
    "createdTime": 1707686435397,
    "modifiedTime": 1756662987716,
    "lastModifiedBy": "KQJsJtxYaymNehvs",
    "compendiumSource": null,
    "duplicateSource": null,
    "exportSource": null
  },
  "_id": "4ODajNno3NSDZEak",
  "sort": 0,
  "ownership": {
    "default": 0
  },
  "_key": "!items!4ODajNno3NSDZEak"
}
