{
  "type": "knight",
  "name": "The Seal Knight",
  "system": {
    "name": "",
    "description": "A Knight’s sworn oath outlasts the stone wall. Yet Seers say in time even words must fall",
    "flavor": "Runic scrolls",
    "flavorLabel1": "Subject",
    "flavorLabel2": "Prophecy"
  },
  "folder": "GKcm4nNi7uY8EQC7",
  "img": "systems/mythicbastionland/tokens/items/knight.png",
  "effects": [],
  "flags": {},
  "_stats": {
    "systemId": "mythicbastionland",
    "systemVersion": "1.0.8",
    "coreVersion": "13.348",
    "createdTime": 1707686408866,
    "modifiedTime": 1756662987716,
    "lastModifiedBy": "KQJsJtxYaymNehvs",
    "compendiumSource": null,
    "duplicateSource": null,
    "exportSource": null
  },
  "_id": "vpZWKLctuVbIUvzb",
  "sort": 0,
  "ownership": {
    "default": 0
  },
  "_key": "!items!vpZWKLctuVbIUvzb"
}
